prompt_genetics/__init__.py
prompt_genetics-0.0.1.dist-info/licenses/LICENSE
prompt_genetics-0.0.1.dist-info/METADATA
prompt_genetics-0.0.1.dist-info/WHEEL
prompt_genetics-0.0.1.dist-info/entry_points.txt
prompt_genetics-0.0.1.dist-info/top_level.txt
prompt_genetics-0.0.1.dist-info/RECORD
